asl_api/__init__.py
asl_api/api_client.py
asl_api/api_response.py
asl_api/configuration.py
asl_api/exceptions.py
asl_api/py.typed
asl_api/rest.py
asl_api/api/__init__.py
asl_api/api/content_v1alpha1_api.py
asl_api/api/core_v1alpha1_api.py
asl_api/api/dbui_v1alpha1_api.py
asl_api/api/workspace_v1alpha1_api.py
asl_api/models/__init__.py
asl_api/models/common_v1alpha1_job_meta.py
asl_api/models/common_v1alpha1_list_meta.py
asl_api/models/common_v1alpha1_object_meta.py
asl_api/models/conflict_error.py
asl_api/models/content_v1alpha1_gold_preset.py
asl_api/models/content_v1alpha1_gold_preset_list.py
asl_api/models/content_v1alpha1_gold_preset_tables_inner.py
asl_api/models/content_v1alpha1_mitre_attack.py
asl_api/models/content_v1alpha1_mitre_sub_technique.py
asl_api/models/content_v1alpha1_mitre_tactic.py
asl_api/models/content_v1alpha1_mitre_technique.py
asl_api/models/content_v1alpha1_mitre_technique_detail.py
asl_api/models/content_v1alpha1_pre_transform_preset.py
asl_api/models/content_v1alpha1_pre_transform_preset_list.py
asl_api/models/content_v1alpha1_pre_transform_preset_list_recommended_presets_inner.py
asl_api/models/content_v1alpha1_preset_data_source_list.py
asl_api/models/content_v1alpha1_preset_data_source_list_items_inner.py
asl_api/models/content_v1alpha1_silver_preset.py
asl_api/models/content_v1alpha1_silver_preset_list.py
asl_api/models/core_v1alpha1_data_source.py
asl_api/models/core_v1alpha1_data_source_field_spec.py
asl_api/models/core_v1alpha1_data_source_field_spec_join.py
asl_api/models/core_v1alpha1_data_source_field_spec_join_with_csv.py
asl_api/models/core_v1alpha1_data_source_list.py
asl_api/models/core_v1alpha1_data_source_spec.py
asl_api/models/core_v1alpha1_data_source_spec_gold.py
asl_api/models/core_v1alpha1_data_source_spec_gold_add_tables_inner.py
asl_api/models/core_v1alpha1_data_source_spec_gold_custom_inner.py
asl_api/models/core_v1alpha1_data_source_spec_gold_preset_overrides_value.py
asl_api-0.0.2.dist-info/METADATA
asl_api-0.0.2.dist-info/WHEEL
asl_api-0.0.2.dist-info/top_level.txt
asl_api-0.0.2.dist-info/RECORD
